aiohcaptcha/__init__.py
aiohcaptcha-0.1.2.dist-info/LICENSE
aiohcaptcha-0.1.2.dist-info/WHEEL
aiohcaptcha-0.1.2.dist-info/METADATA
aiohcaptcha-0.1.2.dist-info/RECORD
