Metadata-Version: 2.1
Name: aiohcaptcha
Version: 0.1.2
Summary: AsyncIO client for the hCaptcha service.
Home-page: https://gitlab.com/mastizada/aiohcaptcha
License: MIT
Keywords: hcaptcha,captcha
Author: Emin Mastizada
Author-email: emin@linux.com
Requires-Python: >=3.6,<4.0
Classifier: Development Status :: 5 - Production/Stable
Classifier: Environment :: Plugins
Classifier: Framework :: AsyncIO
Classifier: License :: OSI Approved :: MIT License
Classifier: Programming Language :: Python :: 3
Classifier: Programming Language :: Python :: 3 :: Only
Classifier: Programming Language :: Python :: 3.6
Classifier: Programming Language :: Python :: 3.7
Classifier: Programming Language :: Python :: 3.8
Classifier: Programming Language :: Python :: 3.9
Classifier: Topic :: Software Development :: Libraries
Classifier: Typing :: Typed
Requires-Dist: aiohttp (>=3.7.3,<4.0.0)
Project-URL: Repository, https://gitlab.com/mastizada/aiohcaptcha
